lstm_dl_model/DataEngine.py
lstm_dl_model/DeepLearningEngine.py
lstm_dl_model/LongShortTremMemoryEngine.py
lstm_dl_model/__init__.py
lstm_dl_model/_main.py
lstm_dl_model/datafeeder.py
lstm_dl_model/sideclasses.py
lstm_dl_model/data/__init__.py
lstm_dl_model/data/data_loader.py
lstm_dl_model/data/dataframe_shifter.py
lstm_dl_model/data/dataset.py
lstm_dl_model/data/scaler.py
lstm_dl_model/data/train_test_spliter.py
lstm_dl_model/data/util.py
lstm_dl_model/lstm/__init__.py
lstm_dl_model/lstm/model.py
lstm_dl_model/training/__init__.py
lstm_dl_model/training/loss_record.py
lstm_dl_model/training/trainer.py
lstm_dl_model/training/utils.py
lstm_dl_model-1.0.0.dist-info/METADATA
lstm_dl_model-1.0.0.dist-info/WHEEL
lstm_dl_model-1.0.0.dist-info/licenses/LICENSE
lstm_dl_model-1.0.0.dist-info/RECORD
